click_plugins.py
click_plugins/__init__.py
click_plugins/core.py
click_plugins-1.1.1.1.dist-info/licenses/AUTHORS.txt
click_plugins-1.1.1.1.dist-info/licenses/LICENSE.txt
click_plugins-1.1.1.1.dist-info/METADATA
click_plugins-1.1.1.1.dist-info/WHEEL
click_plugins-1.1.1.1.dist-info/top_level.txt
click_plugins-1.1.1.1.dist-info/zip-safe
click_plugins-1.1.1.1.dist-info/RECORD
