Metadata-Version: 2.4
Name: click-plugins
Version: 1.1.1.1
Summary: An extension module for click to enable registering CLI commands via setuptools entry-points.
Home-page: https://github.com/click-contrib/click-plugins
Author: Kevin Wurster, Sean Gillies
Author-email: wursterk@gmail.com, sean.gillies@gmail.com
License: New BSD
Keywords: click plugin setuptools entry-point
Classifier: Topic :: Utilities
Classifier: Intended Audience :: Developers
Classifier: Development Status :: 7 - Inactive
Classifier: License :: OSI Approved :: BSD License
Classifier: Programming Language :: Python
Classifier: Programming Language :: Python :: 3
License-File: LICENSE.txt
License-File: AUTHORS.txt
Requires-Dist: click>=4.0
Provides-Extra: dev
Requires-Dist: pytest>=3.6; extra == "dev"
Requires-Dist: pytest-cov; extra == "dev"
Requires-Dist: wheel; extra == "dev"
Requires-Dist: coveralls; extra == "dev"
Dynamic: author
Dynamic: author-email
Dynamic: classifier
Dynamic: description
Dynamic: home-page
Dynamic: keywords
Dynamic: license
Dynamic: license-file
Dynamic: provides-extra
Dynamic: requires-dist
Dynamic: summary
